{
  "$schema": "https://developer.microsoft.com/json-schemas/fabric/item/report/definition/visualContainer/2.7.0/schema.json",
  "name": "c885e55b6d4d92d838a8",
  "position": {
    "x": 186.24720430306277,
    "y": 95.394909521080933,
    "z": 6000,
    "height": 121.13639304264245,
    "width": 186.24720430306277,
    "tabOrder": 6000
  },
  "visual": {
    "visualType": "card",
    "query": {
      "queryState": {
        "Values": {
          "projections": [
            {
              "field": {
                "Measure": {
                  "Expression": {
                    "SourceRef": {
                      "Entity": "Orders"
                    }
                  },
                  "Property": "ProfitPercent"
                }
              },
              "queryRef": "Orders.ProfitPercent",
              "nativeQueryRef": "ProfitPercent"
            }
          ]
        }
      },
      "sortDefinition": {
        "sort": [
          {
            "field": {
              "Measure": {
                "Expression": {
                  "SourceRef": {
                    "Entity": "Orders"
                  }
                },
                "Property": "ProfitPercent"
              }
            },
            "direction": "Descending"
          }
        ],
        "isDefaultSort": true
      }
    },
    "objects": {
      "general": [
        {
          "properties": {}
        }
      ]
    },
    "visualContainerObjects": {
      "title": [
        {
          "properties": {
            "show": {
              "expr": {
                "Literal": {
                  "Value": "true"
                }
              }
            },
            "text": {
              "expr": {
                "Literal": {
                  "Value": "'Profit (%) Across All Time'"
                }
              }
            }
          }
        }
      ]
    },
    "drillFilterOtherVisuals": true
  }
}